MANIFEST.in
README.md
setup.cfg
setup.py
pyshorteners/__init__.py
pyshorteners/exceptions.py
pyshorteners/utils.py
pyshorteners.egg-info/PKG-INFO
pyshorteners.egg-info/SOURCES.txt
pyshorteners.egg-info/dependency_links.txt
pyshorteners.egg-info/requires.txt
pyshorteners.egg-info/top_level.txt
pyshorteners/shorteners/__init__.py
pyshorteners/shorteners/adfly.py
pyshorteners/shorteners/awsm.py
pyshorteners/shorteners/base.py
pyshorteners/shorteners/bitly.py
pyshorteners/shorteners/chilpit.py
pyshorteners/shorteners/clckru.py
pyshorteners/shorteners/dagd.py
pyshorteners/shorteners/googl.py
pyshorteners/shorteners/isgd.py
pyshorteners/shorteners/osdb.py
pyshorteners/shorteners/owly.py
pyshorteners/shorteners/qpsru.py
pyshorteners/shorteners/readability.py
pyshorteners/shorteners/sentala.py
pyshorteners/shorteners/tinyurl.py
pyshorteners/shorteners/wpaco.py