Metadata-Version: 1.1
Name: pyshorteners
Version: 0.6.1
Summary: A Python lib to consume the most used shorteners APIs
Home-page: https://github.com/ellisonleao/pyshorteners/
Author: Ellison Leão
Author-email: ellisonleao@gmail.com
License: MIT
Platform: a
Platform: n
Platform: y
Classifier: Development Status :: 5 - Production/Stable
Classifier: Intended Audience :: Developers
Classifier: Operating System :: OS Independent
Classifier: Programming Language :: Python :: 2
Classifier: Programming Language :: Python :: 3
Classifier: Topic :: Internet :: WWW/HTTP :: Dynamic Content
Classifier: Topic :: Software Development :: Libraries :: Python Modules
